<?xml version="1.0" encoding="UTF-8"?>
<databaseChangeLog
        xmlns="http://www.liquibase.org/xml/ns/dbchangelog"
        xmlns:xsi="http://www.w3.org/2001/XMLSchema-instance"
        xsi:schemaLocation="http://www.liquibase.org/xml/ns/dbchangelog
        http://www.liquibase.org/xml/ns/dbchangelog/dbchangelog-4.23.xsd">

    <changeSet id="007-sikayet-turleri" author="codex">
        <createTable tableName="sikayet_turleri">
            <column name="id" type="BIGINT" autoIncrement="true"><constraints primaryKey="true" nullable="false"/></column>
            <column name="kod" type="VARCHAR(50)"><constraints nullable="false" unique="true"/></column>
            <column name="ad" type="VARCHAR(100)"><constraints nullable="false"/></column>
            <column name="aciklama" type="VARCHAR(255)"/>
            <column name="created_at" type="DATETIME"><constraints nullable="false"/></column>
            <column name="updated_at" type="DATETIME"/>
            <column name="created_by" type="VARCHAR(100)"/>
            <column name="updated_by" type="VARCHAR(100)"/>
            <column name="active" type="BIT" defaultValueBoolean="true"><constraints nullable="false"/></column>
        </createTable>
    </changeSet>

    <changeSet id="008-sikayet-durumlari" author="codex">
        <createTable tableName="sikayet_durumlari">
            <column name="id" type="BIGINT" autoIncrement="true"><constraints primaryKey="true" nullable="false"/></column>
            <column name="kod" type="VARCHAR(50)"><constraints nullable="false" unique="true"/></column>
            <column name="ad" type="VARCHAR(100)"><constraints nullable="false"/></column>
            <column name="final_durum" type="BIT" defaultValueBoolean="false"><constraints nullable="false"/></column>
            <column name="created_at" type="DATETIME"><constraints nullable="false"/></column>
            <column name="updated_at" type="DATETIME"/>
            <column name="created_by" type="VARCHAR(100)"/>
            <column name="updated_by" type="VARCHAR(100)"/>
            <column name="active" type="BIT" defaultValueBoolean="true"><constraints nullable="false"/></column>
        </createTable>
    </changeSet>

    <changeSet id="009-sikayetler" author="codex">
        <createTable tableName="sikayetler">
            <column name="id" type="BIGINT" autoIncrement="true"><constraints primaryKey="true" nullable="false"/></column>
            <column name="sikayet_no" type="VARCHAR(50)"><constraints nullable="false" unique="true"/></column>
            <column name="kisi_id" type="BIGINT"><constraints nullable="false"/></column>
            <column name="sikayet_turu_id" type="BIGINT"><constraints nullable="false"/></column>
            <column name="sikayet_durumu_id" type="BIGINT"><constraints nullable="false"/></column>
            <column name="konu" type="VARCHAR(255)"><constraints nullable="false"/></column>
            <column name="aciklama" type="TEXT"><constraints nullable="false"/></column>
            <column name="oncelik" type="VARCHAR(50)"/>
            <column name="created_at" type="DATETIME"><constraints nullable="false"/></column>
            <column name="updated_at" type="DATETIME"/>
            <column name="created_by" type="VARCHAR(100)"/>
            <column name="updated_by" type="VARCHAR(100)"/>
            <column name="active" type="BIT" defaultValueBoolean="true"><constraints nullable="false"/></column>
        </createTable>
        <createIndex tableName="sikayetler" indexName="idx_sikayet_no"><column name="sikayet_no"/></createIndex>
        <addForeignKeyConstraint baseTableName="sikayetler" baseColumnNames="kisi_id" referencedTableName="kisiler" referencedColumnNames="id" constraintName="fk_sikayet_kisi"/>
        <addForeignKeyConstraint baseTableName="sikayetler" baseColumnNames="sikayet_turu_id" referencedTableName="sikayet_turleri" referencedColumnNames="id" constraintName="fk_sikayet_tur"/>
        <addForeignKeyConstraint baseTableName="sikayetler" baseColumnNames="sikayet_durumu_id" referencedTableName="sikayet_durumlari" referencedColumnNames="id" constraintName="fk_sikayet_durum"/>
    </changeSet>

    <changeSet id="010-sikayet-ekleri" author="codex">
        <createTable tableName="sikayet_dosyalari">
            <column name="id" type="BIGINT" autoIncrement="true"><constraints primaryKey="true" nullable="false"/></column>
            <column name="sikayet_id" type="BIGINT"><constraints nullable="false"/></column>
            <column name="orijinal_dosya_adi" type="VARCHAR(255)"><constraints nullable="false"/></column>
            <column name="sistem_dosya_adi" type="VARCHAR(255)"><constraints nullable="false"/></column>
            <column name="dosya_yolu" type="VARCHAR(500)"><constraints nullable="false"/></column>
            <column name="mime_type" type="VARCHAR(100)"><constraints nullable="false"/></column>
            <column name="dosya_boyutu" type="BIGINT"><constraints nullable="false"/></column>
            <column name="yukleyen_kullanici_id" type="BIGINT"/>
            <column name="created_at" type="DATETIME"><constraints nullable="false"/></column>
            <column name="updated_at" type="DATETIME"/>
            <column name="created_by" type="VARCHAR(100)"/>
            <column name="updated_by" type="VARCHAR(100)"/>
            <column name="active" type="BIT" defaultValueBoolean="true"><constraints nullable="false"/></column>
        </createTable>
        <addForeignKeyConstraint baseTableName="sikayet_dosyalari" baseColumnNames="sikayet_id" referencedTableName="sikayetler" referencedColumnNames="id" constraintName="fk_dosya_sikayet"/>
        <addForeignKeyConstraint baseTableName="sikayet_dosyalari" baseColumnNames="yukleyen_kullanici_id" referencedTableName="kullanicilar" referencedColumnNames="id" constraintName="fk_dosya_kullanici"/>
    </changeSet>

    <changeSet id="011-atama-gecmis-log-sonuc" author="codex">
        <createTable tableName="sikayet_atamalari">
            <column name="id" type="BIGINT" autoIncrement="true"><constraints primaryKey="true" nullable="false"/></column>
            <column name="sikayet_id" type="BIGINT"><constraints nullable="false"/></column>
            <column name="atanan_kullanici_id" type="BIGINT"><constraints nullable="false"/></column>
            <column name="atama_tarihi" type="DATETIME"><constraints nullable="false"/></column>
            <column name="aktif" type="BIT" defaultValueBoolean="true"><constraints nullable="false"/></column>
            <column name="created_at" type="DATETIME"><constraints nullable="false"/></column>
            <column name="updated_at" type="DATETIME"/>
            <column name="created_by" type="VARCHAR(100)"/>
            <column name="updated_by" type="VARCHAR(100)"/>
            <column name="active" type="BIT" defaultValueBoolean="true"><constraints nullable="false"/></column>
        </createTable>
        <createIndex tableName="sikayet_atamalari" indexName="idx_atanan_kullanici"><column name="atanan_kullanici_id"/></createIndex>
        <addForeignKeyConstraint baseTableName="sikayet_atamalari" baseColumnNames="sikayet_id" referencedTableName="sikayetler" referencedColumnNames="id" constraintName="fk_atama_sikayet"/>
        <addForeignKeyConstraint baseTableName="sikayet_atamalari" baseColumnNames="atanan_kullanici_id" referencedTableName="kullanicilar" referencedColumnNames="id" constraintName="fk_atama_kullanici"/>

        <createTable tableName="sikayet_durum_gecmisi">
            <column name="id" type="BIGINT" autoIncrement="true"><constraints primaryKey="true" nullable="false"/></column>
            <column name="sikayet_id" type="BIGINT"><constraints nullable="false"/></column>
            <column name="eski_durum_id" type="BIGINT"/>
            <column name="yeni_durum_id" type="BIGINT"><constraints nullable="false"/></column>
            <column name="degistiren_kullanici_id" type="BIGINT"/>
            <column name="degisim_tarihi" type="DATETIME"><constraints nullable="false"/></column>
            <column name="aciklama" type="VARCHAR(255)"/>
            <column name="created_at" type="DATETIME"><constraints nullable="false"/></column>
            <column name="updated_at" type="DATETIME"/>
            <column name="created_by" type="VARCHAR(100)"/>
            <column name="updated_by" type="VARCHAR(100)"/>
            <column name="active" type="BIT" defaultValueBoolean="true"><constraints nullable="false"/></column>
        </createTable>
        <addForeignKeyConstraint baseTableName="sikayet_durum_gecmisi" baseColumnNames="sikayet_id" referencedTableName="sikayetler" referencedColumnNames="id" constraintName="fk_gecmis_sikayet"/>
        <addForeignKeyConstraint baseTableName="sikayet_durum_gecmisi" baseColumnNames="eski_durum_id" referencedTableName="sikayet_durumlari" referencedColumnNames="id" constraintName="fk_gecmis_eski_durum"/>
        <addForeignKeyConstraint baseTableName="sikayet_durum_gecmisi" baseColumnNames="yeni_durum_id" referencedTableName="sikayet_durumlari" referencedColumnNames="id" constraintName="fk_gecmis_yeni_durum"/>
        <addForeignKeyConstraint baseTableName="sikayet_durum_gecmisi" baseColumnNames="degistiren_kullanici_id" referencedTableName="kullanicilar" referencedColumnNames="id" constraintName="fk_gecmis_kullanici"/>

        <createTable tableName="sikayet_loglari">
            <column name="id" type="BIGINT" autoIncrement="true"><constraints primaryKey="true" nullable="false"/></column>
            <column name="sikayet_id" type="BIGINT"><constraints nullable="false"/></column>
            <column name="islem_tipi" type="VARCHAR(100)"><constraints nullable="false"/></column>
            <column name="mesaj" type="VARCHAR(500)"><constraints nullable="false"/></column>
            <column name="kullanici_id" type="BIGINT"/>
            <column name="islem_tarihi" type="DATETIME"><constraints nullable="false"/></column>
            <column name="created_at" type="DATETIME"><constraints nullable="false"/></column>
            <column name="updated_at" type="DATETIME"/>
            <column name="created_by" type="VARCHAR(100)"/>
            <column name="updated_by" type="VARCHAR(100)"/>
            <column name="active" type="BIT" defaultValueBoolean="true"><constraints nullable="false"/></column>
        </createTable>
        <addForeignKeyConstraint baseTableName="sikayet_loglari" baseColumnNames="sikayet_id" referencedTableName="sikayetler" referencedColumnNames="id" constraintName="fk_log_sikayet"/>

        <createTable tableName="sikayet_sonuclari">
            <column name="id" type="BIGINT" autoIncrement="true"><constraints primaryKey="true" nullable="false"/></column>
            <column name="sikayet_id" type="BIGINT"><constraints nullable="false" unique="true"/></column>
            <column name="sonuc_metin" type="TEXT"><constraints nullable="false"/></column>
            <column name="sonuclandiran_kullanici_id" type="BIGINT"/>
            <column name="sonuclanma_tarihi" type="DATETIME"><constraints nullable="false"/></column>
            <column name="created_at" type="DATETIME"><constraints nullable="false"/></column>
            <column name="updated_at" type="DATETIME"/>
            <column name="created_by" type="VARCHAR(100)"/>
            <column name="updated_by" type="VARCHAR(100)"/>
            <column name="active" type="BIT" defaultValueBoolean="true"><constraints nullable="false"/></column>
        </createTable>
        <addForeignKeyConstraint baseTableName="sikayet_sonuclari" baseColumnNames="sikayet_id" referencedTableName="sikayetler" referencedColumnNames="id" constraintName="fk_sonuc_sikayet"/>
    </changeSet>
</databaseChangeLog>
